base_common_drf/__init__.py
base_common_drf/apps.py
base_common_drf/authentication.py
base_common_drf/migrations/__init__.py
base_common_drf/openapi/__init__.py
base_common_drf/openapi/authentication.py
base_common_drf/openapi/responses.py
base_common_drf-0.4.dist-info/LICENSE
base_common_drf-0.4.dist-info/METADATA
base_common_drf-0.4.dist-info/WHEEL
base_common_drf-0.4.dist-info/top_level.txt
base_common_drf-0.4.dist-info/RECORD
