Metadata-Version: 2.1
Name: base-common-drf
Version: 0.4
Summary: Django app with common implementations for base Angewandte projects using Django REST Framework
License: Apache License, Version 2.0
Classifier: Intended Audience :: Developers
Classifier: Programming Language :: Python :: 3
Requires-Python: >=3.8
License-File: LICENSE
Requires-Dist: django >=4.2
Requires-Dist: djangorestframework >=3.13
Requires-Dist: drf-spectacular >=0.26
